ArgConfigParse/ArgConfigParse.py
ArgConfigParse/__init__.py
ArgConfigParse-0.2.7.dist-info/LICENSE
ArgConfigParse-0.2.7.dist-info/METADATA
ArgConfigParse-0.2.7.dist-info/WHEEL
ArgConfigParse-0.2.7.dist-info/top_level.txt
ArgConfigParse-0.2.7.dist-info/RECORD
