Metadata-Version: 2.1
Name: ArgConfigParse
Version: 0.2.7
Summary: Merge multiple configuraton files and command line arguments into a single configuration
Home-page: https://github.com/txoof/ArgConfigParse
Author: Aaron Ciuffo
Author-email: aaron.ciuffo@gmail.com
License: GP
Keywords: argparse config
Platform: UNKNOWN
Classifier: Development Status :: 4 - Beta
Classifier: Environment :: Console
Classifier: Intended Audience :: Developers
Classifier: License :: OSI Approved :: GNU Lesser General Public License v3 or later (LGPLv3+)
Classifier: Operating System :: OS Independent
Classifier: Programming Language :: Python
Classifier: Topic :: Software Development
Classifier: Topic :: Software Development :: Libraries
Classifier: Topic :: Software Development :: Libraries :: Python Modules
Requires-Python: >3.6
